{"skeleton":{"hash":"Sa6woI5QkZghIIyfG+h+POd66C8","spine":"3.7.93","width":316.86,"height":240,"images":"./images/","audio":"E:/Cty/10+/10/moihon/animation/map6_10/quaitrung8"},"bones":[{"name":"root"},{"name":"Layer 13","parent":"root","y":-30.45},{"name":"Layer 14","parent":"Layer 13","x":-2.75,"y":47.3},{"name":"Layer 14 copy","parent":"Layer 14","x":-55.55,"y":-28.6},{"name":"Layer 16 copy","parent":"Layer 14","x":-35.75,"y":15.4},{"name":"Layer 13 copy 3","parent":"Layer 14","x":-57.2,"y":22},{"name":"Layer 15","parent":"Layer 13 copy 3","x":1.1,"y":23.1},{"name":"Layer 16","parent":"Layer 13","x":3.8,"y":47.3,"scaleX":-1},{"name":"Layer 14 copy2","parent":"Layer 16","x":-55.55,"y":-28.6},{"name":"Layer 16 copy2","parent":"Layer 16","x":-35.75,"y":15.4},{"name":"Layer 13 copy 4","parent":"Layer 16","x":-57.2,"y":22},{"name":"Layer 17","parent":"Layer 13 copy 4","x":1.1,"y":23.1}],"slots":[{"name":"Layer 14","bone":"Layer 15","attachment":"Layer 14"},{"name":"Layer 15","bone":"Layer 17","attachment":"Layer 14"},{"name":"Layer 13 copy 3","bone":"Layer 13 copy 3","attachment":"Layer 13 copy 3"},{"name":"Layer 13 copy 4","bone":"Layer 13 copy 4","attachment":"Layer 13 copy 3"},{"name":"Layer 16 copy","bone":"Layer 16 copy","attachment":"Layer 16 copy"},{"name":"Layer 16 copy2","bone":"Layer 16 copy2","attachment":"Layer 16 copy"},{"name":"Layer 14 copy","bone":"Layer 14 copy","attachment":"Layer 14 copy"},{"name":"Layer 14 copy2","bone":"Layer 14 copy2","attachment":"Layer 14 copy"},{"name":"Layer 13","bone":"Layer 13","attachment":"Layer 13"}],"skins":{"default":{"Layer 13":{"Layer 13":{"x":0.6,"y":-3.6,"width":105,"height":137}},"Layer 13 copy 3":{"Layer 13 copy 3":{"type":"mesh","uvs":[1,0.06435,1,1,0,1,0.01065,0.06653],"triangles":[3,0,1,2,3,1],"vertices":[34.05,14.26,34.05,-63.4,-33.95,-63.4,-33.23,14.08],"hull":4,"edges":[2,4,4,6,2,0,6,0],"width":68,"height":83}},"Layer 13 copy 4":{"Layer 13 copy 3":{"type":"mesh","uvs":[1,0.06435,1,1,0,1,0.01065,0.06653],"triangles":[3,0,1,2,3,1],"vertices":[34.05,14.26,34.05,-63.4,-33.95,-63.4,-33.23,14.08],"hull":4,"edges":[2,4,4,6,2,0,6,0],"width":68,"height":83}},"Layer 14":{"Layer 14":{"x":-0.05,"y":19.5,"width":32,"height":62}},"Layer 14 copy":{"Layer 14 copy":{"x":-21.6,"y":-26.8,"width":156,"height":178}},"Layer 14 copy2":{"Layer 14 copy":{"x":-21.6,"y":-26.8,"width":156,"height":178}},"Layer 15":{"Layer 14":{"x":-0.05,"y":19.5,"width":32,"height":62}},"Layer 16 copy":{"Layer 16 copy":{"x":-3.9,"y":9.2,"width":47,"height":74}},"Layer 16 copy2":{"Layer 16 copy":{"x":-3.9,"y":9.2,"width":47,"height":74}}}},"animations":{"idle":{"bones":{"Layer 13 copy 3":{"translate":[{"time":0,"x":0,"y":0},{"time":0.0333,"x":0,"y":-2.8},{"time":0.0667,"x":0,"y":0},{"time":0.1,"x":0,"y":-2.8},{"time":0.1333,"x":0,"y":0},{"time":0.1667,"x":0,"y":-2.8},{"time":0.2,"x":0,"y":0},{"time":0.2333,"x":0,"y":-2.8},{"time":0.2667,"x":0,"y":0},{"time":0.3,"x":0,"y":-2.8},{"time":0.3333,"x":0,"y":0}]},"Layer 15":{"scale":[{"time":0,"x":1,"y":0.804},{"time":0.0333,"x":1,"y":2.778},{"time":0.0667,"x":1,"y":0.804},{"time":0.1,"x":1,"y":2.778},{"time":0.1333,"x":1,"y":0.804},{"time":0.1667,"x":1,"y":2.778},{"time":0.2,"x":1,"y":0.804},{"time":0.2333,"x":1,"y":2.778},{"time":0.2667,"x":1,"y":0.804},{"time":0.3,"x":1,"y":2.778},{"time":0.3333,"x":1,"y":0.804}]},"Layer 14 copy":{"translate":[{"time":0,"x":0,"y":0},{"time":0.1333,"x":0,"y":-4.36},{"time":0.3333,"x":0,"y":0}]},"Layer 16 copy":{"translate":[{"time":0,"x":1.25,"y":0},{"time":0.1,"x":0,"y":5.09},{"time":0.2,"x":1.25,"y":0},{"time":0.2667,"x":0,"y":5.09},{"time":0.3333,"x":1.25,"y":0}]},"Layer 14 copy2":{"translate":[{"time":0,"x":0,"y":0},{"time":0.1333,"x":0,"y":-4.36},{"time":0.3333,"x":0,"y":0}]},"Layer 16 copy2":{"translate":[{"time":0,"x":1.25,"y":0},{"time":0.1,"x":0,"y":5.09},{"time":0.2,"x":1.25,"y":0},{"time":0.2667,"x":0,"y":5.09},{"time":0.3333,"x":1.25,"y":0}]},"Layer 17":{"scale":[{"time":0,"x":1,"y":0.804},{"time":0.0333,"x":1,"y":2.778},{"time":0.0667,"x":1,"y":0.804},{"time":0.1,"x":1,"y":2.778},{"time":0.1333,"x":1,"y":0.804},{"time":0.1667,"x":1,"y":2.778},{"time":0.2,"x":1,"y":0.804},{"time":0.2333,"x":1,"y":2.778},{"time":0.2667,"x":1,"y":0.804},{"time":0.3,"x":1,"y":2.778},{"time":0.3333,"x":1,"y":0.804}]},"Layer 13 copy 4":{"translate":[{"time":0,"x":0,"y":0},{"time":0.0333,"x":0,"y":-2.8},{"time":0.0667,"x":0,"y":0},{"time":0.1,"x":0,"y":-2.8},{"time":0.1333,"x":0,"y":0},{"time":0.1667,"x":0,"y":-2.8},{"time":0.2,"x":0,"y":0},{"time":0.2333,"x":0,"y":-2.8},{"time":0.2667,"x":0,"y":0},{"time":0.3,"x":0,"y":-2.8},{"time":0.3333,"x":0,"y":0}]}}}}}