{"skeleton":{"hash":"YQkHW716sae1/CQwbAesuYYs67I","spine":"3.7.94","width":380,"height":279,"images":"./images/","audio":"E:/Cty/10+/10_maybay/3/animation/map11_15/trung2"},"bones":[{"name":"root"},{"name":"bone","parent":"root"},{"name":"D01Boss0 (2)_06","parent":"bone","y":45.7},{"name":"D01Boss0 (2)_07","parent":"D01Boss0 (2)_06","x":-0.39,"y":-75.46},{"name":"xuongdenhan","parent":"bone","x":-25.42,"y":38.66},{"name":"D01Boss0 (2)_16 copy","parent":"xuongdenhan","length":53.36,"rotation":114.69,"x":-18.77,"y":-19.16},{"name":"D01Boss0 (2)_12","parent":"xuongdenhan","length":44.96,"rotation":-105.12,"x":-8.99,"y":-52},{"name":"xuongdenhan2","parent":"bone","x":25.47,"y":38.66,"scaleX":-1},{"name":"D01Boss0 (2)_16 copy2","parent":"xuongdenhan2","length":53.36,"rotation":114.69,"x":-18.77,"y":-19.16},{"name":"D01Boss0 (2)_13","parent":"xuongdenhan2","length":44.96,"rotation":-105.12,"x":-8.99,"y":-52}],"slots":[{"name":"D01Boss0 (2)_12","bone":"D01Boss0 (2)_12","attachment":"D01Boss0 (2)_12"},{"name":"D01Boss0 (2)_13","bone":"D01Boss0 (2)_13","attachment":"D01Boss0 (2)_12"},{"name":"D01Boss0 (2)_07","bone":"D01Boss0 (2)_07","attachment":"D01Boss0 (2)_07"},{"name":"D01Boss0 (2)_16 copy","bone":"D01Boss0 (2)_16 copy","attachment":"D01Boss0 (2)_16 copy"},{"name":"D01Boss0 (2)_16 copy2","bone":"D01Boss0 (2)_16 copy2","attachment":"D01Boss0 (2)_16 copy"},{"name":"D01Boss0 (2)_06","bone":"D01Boss0 (2)_06","attachment":"D01Boss0 (2)_06"}],"skins":{"default":{"D01Boss0 (2)_06":{"D01Boss0 (2)_06":{"x":1.64,"y":12.18,"width":380,"height":198}},"D01Boss0 (2)_07":{"D01Boss0 (2)_07":{"x":0.03,"y":-18.36,"width":72,"height":68}},"D01Boss0 (2)_12":{"D01Boss0 (2)_12":{"x":51.8,"y":6.8,"rotation":105.12,"width":48,"height":114}},"D01Boss0 (2)_13":{"D01Boss0 (2)_12":{"x":51.8,"y":6.8,"rotation":105.12,"width":48,"height":114}},"D01Boss0 (2)_16 copy":{"D01Boss0 (2)_16 copy":{"x":65.18,"y":10.41,"rotation":-114.69,"width":109,"height":145}},"D01Boss0 (2)_16 copy2":{"D01Boss0 (2)_16 copy":{"x":65.18,"y":10.41,"rotation":-114.69,"width":109,"height":145}}}},"animations":{"idle":{"bones":{"D01Boss0 (2)_06":{"translate":[{"time":0,"x":0,"y":0},{"time":0.2,"x":0,"y":-2.36},{"time":0.4,"x":0,"y":0}]},"D01Boss0 (2)_07":{"translate":[{"time":0,"x":0,"y":0,"curve":[0.25,0,0.75,1]},{"time":0.2,"x":0,"y":4.31,"curve":[0.25,0,0.75,1]},{"time":0.4,"x":0,"y":0}]},"bone":{"translate":[{"time":0,"x":0,"y":-6.73}]},"D01Boss0 (2)_12":{"translate":[{"time":0,"x":0,"y":4.09,"curve":[0.351,0.4,0.757,1]},{"time":0.1333,"x":0,"y":0,"curve":[0.25,0,0.75,1]},{"time":0.3333,"x":0,"y":5.71,"curve":[0.265,0,0.618,0.43]},{"time":0.4,"x":0,"y":4.09}]},"D01Boss0 (2)_16 copy":{"translate":[{"time":0,"x":0,"y":2,"curve":[0.375,0.5,0.75,1]},{"time":0.1,"x":0,"y":3.43,"curve":[0.25,0,0.75,1]},{"time":0.3,"x":0,"y":0.57,"curve":[0.25,0,0.625,0.5]},{"time":0.4,"x":0,"y":2}]},"D01Boss0 (2)_16 copy2":{"translate":[{"time":0,"x":0,"y":2,"curve":[0.375,0.5,0.75,1]},{"time":0.1,"x":0,"y":3.43,"curve":[0.25,0,0.75,1]},{"time":0.3,"x":0,"y":0.57,"curve":[0.25,0,0.625,0.5]},{"time":0.4,"x":0,"y":2}]},"D01Boss0 (2)_13":{"translate":[{"time":0,"x":0,"y":4.09,"curve":[0.351,0.4,0.757,1]},{"time":0.1333,"x":0,"y":0,"curve":[0.25,0,0.75,1]},{"time":0.3333,"x":0,"y":5.71,"curve":[0.265,0,0.618,0.43]},{"time":0.4,"x":0,"y":4.09}]}}},"idle2":{"bones":{"D01Boss0 (2)_06":{"translate":[{"time":0,"x":0,"y":0},{"time":0.2,"x":0,"y":-2.36},{"time":0.4,"x":0,"y":0}]},"D01Boss0 (2)_07":{"translate":[{"time":0,"x":0,"y":0,"curve":[0.25,0,0.75,1]},{"time":0.2,"x":0,"y":4.31,"curve":[0.25,0,0.75,1]},{"time":0.4,"x":0,"y":0}]},"bone":{"translate":[{"time":0,"x":0,"y":-6.73}]},"D01Boss0 (2)_12":{"translate":[{"time":0,"x":0,"y":4.09,"curve":[0.351,0.4,0.757,1]},{"time":0.1333,"x":0,"y":0,"curve":[0.25,0,0.75,1]},{"time":0.3333,"x":0,"y":5.71,"curve":[0.265,0,0.618,0.43]},{"time":0.4,"x":0,"y":4.09}]},"D01Boss0 (2)_16 copy":{"rotate":[{"time":0,"angle":0},{"time":0.0333,"angle":3.8},{"time":0.0667,"angle":0.42},{"time":0.1,"angle":3.8},{"time":0.1333,"angle":0.42},{"time":0.4,"angle":0}],"translate":[{"time":0,"x":0,"y":2,"curve":[0.375,0.5,0.75,1]},{"time":0.1,"x":0,"y":3.43,"curve":[0.25,0,0.75,1]},{"time":0.3,"x":0,"y":0.57,"curve":[0.25,0,0.625,0.5]},{"time":0.4,"x":0,"y":2}]},"D01Boss0 (2)_16 copy2":{"rotate":[{"time":0,"angle":0},{"time":0.0333,"angle":3.8},{"time":0.0667,"angle":0.42},{"time":0.1,"angle":3.8},{"time":0.1333,"angle":0.42},{"time":0.4,"angle":0}],"translate":[{"time":0,"x":0,"y":2,"curve":[0.375,0.5,0.75,1]},{"time":0.1,"x":0,"y":3.43,"curve":[0.25,0,0.75,1]},{"time":0.3,"x":0,"y":0.57,"curve":[0.25,0,0.625,0.5]},{"time":0.4,"x":0,"y":2}]},"D01Boss0 (2)_13":{"translate":[{"time":0,"x":0,"y":4.09,"curve":[0.351,0.4,0.757,1]},{"time":0.1333,"x":0,"y":0,"curve":[0.25,0,0.75,1]},{"time":0.3333,"x":0,"y":5.71,"curve":[0.265,0,0.618,0.43]},{"time":0.4,"x":0,"y":4.09}]}}}}}